Workbook
Name aporte: Sheet1!$D$8
Name patrimonio: Sheet1!$D$11
Name qtd_anos: Sheet1!$D$9
Name rendimento_carteira: Sheet1!$D$4
Name sugestao_investimento: Sheet1!$D$5
Name taxa_mensal: Sheet1!$D$10

Sheet Sheet1
B2: configurações
B3: salario | D3: 5000
B4: rendimento carteira | D4: 0.009
B5: sugestão de investimento | D5: =D3*30% -> 1500
B7: investimento mensal
B8: quanto investir por mes | D8: 500
B9: por quantos anos | D9: 5
B10: taxa de rendimento mensal | D10: 0.01079
B11: patrimonio acumulado | D11: =FV(taxa_mensal,qtd_anos*12,aporte*-1) -> 41888.457
B12: dividendos mensais | D12: =patrimonio*rendimento_carteira -> 376.99611
B14: cenarios | D14: dividendo
B15: quanto em 2 anos | C15: =FV(taxa_mensal,A16*12,aporte*-1) -> 13613.814 | D15: =C15*rendimento_carteira -> 122.52432
A16: 2 | B16: quanto em 5 anos | C16: =FV(taxa_mensal,A17*12,aporte*-1) -> 41888.457 | D16: =C16*rendimento_carteira -> 376.99611
A17: 5 | B17: quanto em 10 anos | C17: =FV(taxa_mensal,A18*12,aporte*-1) -> 121642.11 | D17: =C17*rendimento_carteira -> 1094.779
A18: 10 | B18: quanto em 20 anos | C18: =FV(taxa_mensal,A19*12,aporte*-1) -> 562599.2 | D18: =C18*rendimento_carteira -> 5063.3928
A19: 20 | B19: quanto em 30 anos | C19: =FV(taxa_mensal,A20*12,aporte*-1) -> 2161084.8 | D19: =C19*rendimento_carteira -> 19449.763
A20: 30
B23: perfil | C23: moderado
B24: valor a ser investido por mês | C24: =aporte -> 500
B26: tipo de fii | C26: percentual sugerido | D26: valores
B27: papel | C27: =VLOOKUP($C$23&"-"&B27,Sheet2!$A$4:$D$22,4,FALSE) -> 0.32 | D27: =C27*$C$24 -> 160
B28: tijolo | C28: =VLOOKUP($C$23&"-"&B28,Sheet2!$A$4:$D$22,4,FALSE) -> 0.35 | D28: =C28*$C$24 -> 175
B29: hibridos | C29: =VLOOKUP($C$23&"-"&B29,Sheet2!$A$4:$D$22,4,FALSE) -> 0.08 | D29: =C29*$C$24 -> 40
B30: fofs | C30: =VLOOKUP($C$23&"-"&B30,Sheet2!$A$4:$D$22,4,FALSE) -> 0.05 | D30: =C30*$C$24 -> 25
B31: desenvolvimento | C31: =VLOOKUP($C$23&"-"&B31,Sheet2!$A$4:$D$22,4,FALSE) -> 0.1 | D31: =C31*$C$24 -> 50
B32: hotelarias | C32: =VLOOKUP($C$23&"-"&B32,Sheet2!$A$4:$D$22,4,FALSE) -> 0.1 | D32: =C32*$C$24 -> 50
D33: =SUM(D27:D32) -> 500

Sheet Sheet2
A4: chave | B4: perfil | C4: tipo de fii | D4: %
A5: =B5&"-"&C5 -> conservador-papel | B5: conservador | C5: papel | D5: 0.3
A6: =B6&"-"&C6 -> conservador-tijolo | B6: conservador | C6: tijolo | D6: 0.5
A7: =B7&"-"&C7 -> conservador-hibridos | B7: conservador | C7: hibridos | D7: 0.1
A8: =B8&"-"&C8 -> conservador-fofs | B8: conservador | C8: fofs | D8: 0.1
A9: =B9&"-"&C9 -> conservador-desenvolvimento | B9: conservador | C9: desenvolvimento | D9: 0
A10: =B10&"-"&C10 -> conservador-hotelarias | B10: conservador | C10: hotelarias | D10: 0
A11: =B11&"-"&C11 -> moderado-papel | B11: moderado | C11: papel | D11: 0.32
A12: =B12&"-"&C12 -> moderado-tijolo | B12: moderado | C12: tijolo | D12: 0.35
A13: =B13&"-"&C13 -> moderado-hibridos | B13: moderado | C13: hibridos | D13: 0.08
A14: =B14&"-"&C14 -> moderado-fofs | B14: moderado | C14: fofs | D14: 0.05
A15: =B15&"-"&C15 -> moderado-desenvolvimento | B15: moderado | C15: desenvolvimento | D15: 0.1
A16: =B16&"-"&C16 -> moderado-hotelarias | B16: moderado | C16: hotelarias | D16: 0.1
... A22: =B22&"-"&C22 -> agressivo-hotelarias | B22: agressivo | C22: hotelarias | D22: 0.1
